flask_satella_metrics/__init__.py
flask_satella_metrics/prometheus_exporter.py
flask_satella_metrics-1.6.0.dist-info/LICENSE
flask_satella_metrics-1.6.0.dist-info/METADATA
flask_satella_metrics-1.6.0.dist-info/WHEEL
flask_satella_metrics-1.6.0.dist-info/top_level.txt
flask_satella_metrics-1.6.0.dist-info/RECORD
