Metadata-Version: 2.1
Name: flask-satella-metrics
Version: 1.6.0
Summary: A library to metric your Flask app using Satella
Home-page: https://github.com/piotrmaslanka/flask-satella-metrics
Author: Piotr Maślanka
Author-email: pmaslanka@smok.co
Project-URL: Documentation, https://flask-satella-metrics.readthedocs.io/
Keywords: flask,satella,metrics,instrumentation,prometheus
Classifier: Programming Language :: Python
Classifier: Programming Language :: Python :: 3.5
Classifier: Programming Language :: Python :: 3.6
Classifier: Programming Language :: Python :: 3.7
Classifier: Programming Language :: Python :: 3.8
Classifier: Programming Language :: Python :: 3.9
Classifier: Programming Language :: Python :: 3.10
Classifier: Programming Language :: Python :: 3.11
Classifier: Programming Language :: Python :: Implementation :: CPython
Classifier: Programming Language :: Python :: Implementation :: PyPy
Classifier: Operating System :: POSIX
Classifier: Operating System :: OS Independent
Classifier: Development Status :: 5 - Production/Stable
Classifier: License :: OSI Approved :: MIT License
Classifier: Topic :: Software Development :: Libraries
Requires-Python: !=2.7.*,!=3.0.*,!=3.1.*,!=3.2.*,!=3.3.*,!=3.4.*
License-File: LICENSE
Requires-Dist: satella>=2.26.3
Requires-Dist: flask
